config/Config.py
config/__init__.py
config/config.sample.yml
recording/Record.py
recording/__init__.py
stt_watson/SttWatson.py
stt_watson/SttWatsonAbstractListener.py
stt_watson/SttWatsonLogListener.py
stt_watson/__init__.py
stt_watson/__main__.py
stt_watson-1.0.3.dist-info/DESCRIPTION.rst
stt_watson-1.0.3.dist-info/METADATA
stt_watson-1.0.3.dist-info/RECORD
stt_watson-1.0.3.dist-info/WHEEL
stt_watson-1.0.3.dist-info/entry_points.txt
stt_watson-1.0.3.dist-info/metadata.json
stt_watson-1.0.3.dist-info/top_level.txt
utils/SignalHandler.py
utils/Singleton.py
utils/Utils.py
utils/__init__.py
watson_client/Client.py
watson_client/__init__.py
watson_client/websocket/WSInterfaceFactory.py
watson_client/websocket/WSInterfaceProtocol.py
watson_client/websocket/__init__.py
