Metadata-Version: 2.0
Name: stt-watson
Version: 1.0.3
Summary: Continuous speech to text using watson in python with websocket and record from microphone
Home-page: https://github.com/HomeHabbit/stt-watson
Author: Arthur Halet
Author-email: arthurh.halet@gmail.com
License: MIT
Keywords: text-to-speech watson websocket
Platform: ALL
Classifier: Topic :: Multimedia :: Sound/Audio :: Analysis
Classifier: Topic :: Multimedia :: Sound/Audio :: Capture/Recording
Classifier: Topic :: Software Development :: Libraries
Classifier: License :: OSI Approved :: MIT License
Requires-Dist: Twisted (>=13.2.0)
Requires-Dist: autobahn (>=0.10.9)
Requires-Dist: pyOpenSSL (>=0.13.1)
Requires-Dist: pyaudio (>=0.2.9)
Requires-Dist: pyyaml (>=3.08)
Requires-Dist: requests (>=2.8.1)
Requires-Dist: txaio (>=2.0.4)
